LICENSE.txt
README.rst
setup.cfg
setup.py
makinage/__init__.py
makinage/config.py
makinage/makinage.py
makinage/operator.py
makinage/util.py
makinage.egg-info/PKG-INFO
makinage.egg-info/SOURCES.txt
makinage.egg-info/dependency_links.txt
makinage.egg-info/entry_points.txt
makinage.egg-info/requires.txt
makinage.egg-info/top_level.txt
makinage/data/__init__.py
makinage/data/pull.py
makinage/driver/__init__.py
makinage/driver/app_sink.py
makinage/driver/app_source.py
makinage/encoding/__init__.py
makinage/encoding/json.py
makinage/encoding/none.py
makinage/encoding/pickle.py
makinage/encoding/string.py
makinage/model_publisher/__init__.py
makinage/model_publisher/model_publisher.py
makinage/sample/__init__.py
makinage/sample/functions.py
makinage/sample/mlflow_zero_model.py
makinage/sample/processor.py
makinage/sample/serve.py
makinage/serve/__init__.py
makinage/serve/serve.py
tests/__init__.py
tests/test_config.py
tests/test_operators.py
tests/test_serve.py
tests/test_utils.py
tests/driver/__init__.py
tests/driver/test_app_sink.py
tests/driver/test_app_source.py
tests/encoding/__init__.py
tests/encoding/test_json.py
tests/encoding/test_none.py