Metadata-Version: 2.1
Name: makinage
Version: 0.8.0
Summary: Reactive data science
Home-page: https://github.com/maki-nage/makinage.git
Author: Romain Picard
Author-email: romain.picard@oakbits.com
License: MIT
Project-URL: Documentation, https://makinage.readthedocs.io
Platform: any
Classifier: Development Status :: 3 - Alpha
Classifier: License :: OSI Approved :: MIT License
Classifier: Intended Audience :: Developers
Classifier: Programming Language :: Python :: 3
Classifier: Topic :: Scientific/Engineering :: Artificial Intelligence
License-File: LICENSE.txt
